container_manager_mcp/__init__.py
container_manager_mcp/__main__.py
container_manager_mcp/container_manager.py
container_manager_mcp/container_manager_agent.py
container_manager_mcp/container_manager_mcp.py
container_manager_mcp/mcp_config.json
container_manager_mcp/middlewares.py
container_manager_mcp/utils.py
container_manager_mcp/skills/container-manager-compose/SKILL.md
container_manager_mcp/skills/container-manager-containers/SKILL.md
container_manager_mcp/skills/container-manager-containers/troubleshoot.md
container_manager_mcp/skills/container-manager-images/SKILL.md
container_manager_mcp/skills/container-manager-info/SKILL.md
container_manager_mcp/skills/container-manager-logs/SKILL.md
container_manager_mcp/skills/container-manager-networks/SKILL.md
container_manager_mcp/skills/container-manager-swarm/SKILL.md
container_manager_mcp/skills/container-manager-swarm/orchestrate.md
container_manager_mcp/skills/container-manager-system/SKILL.md
container_manager_mcp/skills/container-manager-volumes/SKILL.md
container_manager_mcp-1.2.12.dist-info/licenses/LICENSE
scripts/validate_a2a_agent.py
scripts/validate_agent.py
container_manager_mcp-1.2.12.dist-info/METADATA
container_manager_mcp-1.2.12.dist-info/WHEEL
container_manager_mcp-1.2.12.dist-info/entry_points.txt
container_manager_mcp-1.2.12.dist-info/top_level.txt
container_manager_mcp-1.2.12.dist-info/RECORD
