Metadata-Version: 2.4
Name: container-manager-mcp
Version: 1.2.12
Summary: Container Manager - manage Docker, Docker Swarm, and Podman containers. MCP+A2A Servers Out of the Box!
Author-email: Audel Rouhi <knucklessg1@gmail.com>
License: MIT
Classifier: Development Status :: 5 - Production/Stable
Classifier: License :: Public Domain
Classifier: Environment :: Console
Classifier: Operating System :: POSIX :: Linux
Classifier: Programming Language :: Python :: 3
Requires-Python: >=3.10
License-File: LICENSE
Requires-Dist: requests>=2.28.1
Requires-Dist: fastmcp>=3.0.0b1
Requires-Dist: eunomia-mcp>=0.3.10
Requires-Dist: podman>=5.6.0
Provides-Extra: podman
Requires-Dist: podman>=5.6.0; extra == "podman"
Provides-Extra: docker
Requires-Dist: docker>=7.1.0; extra == "docker"
Provides-Extra: a2a
Requires-Dist: pydantic-ai-slim[a2a,ag-ui,anthropic,fastmcp,google,huggingface,openai,web]>=1.32.0; extra == "a2a"
Requires-Dist: pydantic-ai-skills; extra == "a2a"
Requires-Dist: fastapi>=0.128.0; extra == "a2a"
Provides-Extra: all
Requires-Dist: requests>=2.28.1; extra == "all"
Requires-Dist: fastmcp>=3.0.0b1; extra == "all"
Requires-Dist: eunomia-mcp>=0.3.10; extra == "all"
Requires-Dist: docker>=7.1.0; extra == "all"
Requires-Dist: podman>=5.6.0; extra == "all"
Requires-Dist: pydantic-ai-slim[a2a,ag-ui,anthropic,fastmcp,google,huggingface,openai,web]>=1.32.0; extra == "all"
Requires-Dist: pydantic-ai-skills; extra == "all"
Requires-Dist: fastapi>=0.128.0; extra == "all"
Dynamic: license-file
